pysr_abc_container/__init__.py
pysr_abc_container-1.0.0.dist-info/METADATA
pysr_abc_container-1.0.0.dist-info/WHEEL
pysr_abc_container-1.0.0.dist-info/RECORD
