Metadata-Version: 2.1
Name: pysr-abc-container
Version: 1.0.0
Summary: Dependecy Injection Container Abstractions
Author: Alexey Volkov
Author-email: webwizardry@hotmail.com
Requires-Python: >=3.12,<4.0
Classifier: Programming Language :: Python :: 3
Classifier: Programming Language :: Python :: 3.12
